LICENSE
MANIFEST.in
README.md
requirements.txt
setup.cfg
setup.py
src/os_dbnetget/VERSION
src/os_dbnetget/__init__.py
src/os_dbnetget/cmdline.py
src/os_dbnetget/exceptions.py
src/os_dbnetget/utils.py
src/os_dbnetget.egg-info/PKG-INFO
src/os_dbnetget.egg-info/SOURCES.txt
src/os_dbnetget.egg-info/dependency_links.txt
src/os_dbnetget.egg-info/entry_points.txt
src/os_dbnetget.egg-info/not-zip-safe
src/os_dbnetget.egg-info/requires.txt
src/os_dbnetget.egg-info/top_level.txt
src/os_dbnetget/clients/__init__.py
src/os_dbnetget/clients/client.py
src/os_dbnetget/clients/sync_client.py
src/os_dbnetget/clients/tornado_client.py
src/os_dbnetget/commands/__init__.py
src/os_dbnetget/commands/qdb/__init__.py
src/os_dbnetget/commands/qdb/default_runner.py
src/os_dbnetget/commands/qdb/m3_runner.py
src/os_dbnetget/commands/qdb/processor.py
src/os_dbnetget/commands/qdb/tornado_runner.py
src/os_dbnetget/commands/qdb/get/__init__.py
src/os_dbnetget/commands/qdb/get/default_get.py
src/os_dbnetget/commands/qdb/get/m3_get.py
src/os_dbnetget/commands/qdb/get/processor.py
src/os_dbnetget/commands/qdb/get/tornado_get.py
src/os_dbnetget/commands/qdb/test/__init__.py
src/os_dbnetget/commands/qdb/test/default_test.py
src/os_dbnetget/commands/qdb/test/m3_test.py
src/os_dbnetget/commands/qdb/test/processor.py
src/os_dbnetget/commands/qdb/test/tornado_test.py
tests/__init__.py
tests/cmd_runner.py
tests/conftest.py
tests/utils.py
tests/fake_server/__init__.py
tests/fake_server/qdb_server.py
tests/fake_server/tornado_qdb_server.py
tests/test_m3/__init__.py
tests/test_m3/test_cmdline.py
tests/test_m3/test_m3_engine.py
tests/test_main/__init__.py
tests/test_main/test_cmdline.py
tests/test_main/test_sync_client.py
tests/test_main/test_utils.py
tests/test_main/for_test_module_utils/__init__.py
tests/test_main/for_test_module_utils/test_mod1/__init__.py
tests/test_main/for_test_module_utils/test_mod1/class_a.py
tests/test_main/for_test_module_utils/test_mod1/class_b.py
tests/test_main/for_test_module_utils/test_mod2/__init__.py
tests/test_main/for_test_module_utils/test_mod2/import_error.py
tests/test_main/for_test_module_utils/test_mod2/test_mod1/__init__.py
tests/test_tornado/__init__.py
tests/test_tornado/test_cmdline.py
tests/test_tornado/test_tornado_client.py